LICENSE
README.md
pyproject.toml
event_pipeline/__init__.py
event_pipeline/arts.py
event_pipeline/base.py
event_pipeline/conf.py
event_pipeline/constants.py
event_pipeline/decorators.py
event_pipeline/default_batch_processors.py
event_pipeline/exceptions.py
event_pipeline/fields.py
event_pipeline/import_utils.py
event_pipeline/pipeline.py
event_pipeline/py.typed
event_pipeline/result.py
event_pipeline/settings.py
event_pipeline/task.py
event_pipeline/utils.py
event_pipeline.egg-info/PKG-INFO
event_pipeline.egg-info/SOURCES.txt
event_pipeline.egg-info/dependency_links.txt
event_pipeline.egg-info/requires.txt
event_pipeline.egg-info/top_level.txt
event_pipeline/backends/__init__.py
event_pipeline/backends/connection.py
event_pipeline/backends/store.py
event_pipeline/backends/connectors/__init__.py
event_pipeline/backends/connectors/dummy.py
event_pipeline/backends/connectors/hdfs_connector.py
event_pipeline/backends/connectors/redis.py
event_pipeline/backends/connectors/sqlite.py
event_pipeline/backends/stores/__init__.py
event_pipeline/backends/stores/hdfs_store.py
event_pipeline/backends/stores/inmemory_store.py
event_pipeline/backends/stores/redis_store.py
event_pipeline/backends/stores/sqlite_store.py
event_pipeline/executors/__init__.py
event_pipeline/executors/default_executor.py
event_pipeline/executors/grpc_executor.py
event_pipeline/executors/hadoop_executer.py
event_pipeline/executors/message.py
event_pipeline/executors/remote_executor.py
event_pipeline/executors/rpc_executor.py
event_pipeline/manager/__init__.py
event_pipeline/manager/base.py
event_pipeline/manager/grpc_manager.py
event_pipeline/manager/remote_manager.py
event_pipeline/manager/rpc_manager.py
event_pipeline/mixins/__init__.py
event_pipeline/mixins/backend.py
event_pipeline/mixins/identity.py
event_pipeline/mixins/schedule.py
event_pipeline/mixins/utils/__init__.py
event_pipeline/mixins/utils/connector.py
event_pipeline/parser/__init__.py
event_pipeline/parser/ast.py
event_pipeline/parser/grammar.py
event_pipeline/parser/lexer.py
event_pipeline/parser/parsetab.py
event_pipeline/protos/__init__.py
event_pipeline/protos/task_pb2.py
event_pipeline/protos/task_pb2.pyi
