Metadata-Version: 2.4
Name: event_pipeline
Version: 2.0.0
Summary: Simple tool for writing events and pipelines in python
Author-email: nshaibu <nafiushaibu1@gmail.com>
License:                     GNU GENERAL PUBLIC LICENSE
Project-URL: Issue Tracker, https://github.com/nshaibu/event_pipeline/issues
Project-URL: CI, https://github.com/nshaibu/event_pipeline/actions
Keywords: pipeline,events,concurrency,data,pointy,pointy lang,event-pipeline,redis
Classifier: Development Status :: 4 - Beta
Classifier: Environment :: Console
Classifier: Intended Audience :: Developers
Classifier: License :: OSI Approved :: Apache Software License
Classifier: Operating System :: OS Independent
Classifier: Programming Language :: Python
Classifier: Programming Language :: Python :: 3
Classifier: Programming Language :: Python :: 3.8
Classifier: Programming Language :: Python :: 3.9
Classifier: Programming Language :: Python :: 3.10
Classifier: Programming Language :: Python :: 3.11
Classifier: Programming Language :: Python :: 3.12
Classifier: Topic :: Software Development :: Libraries :: Python Modules
Requires-Python: >=3.8
License-File: LICENSE
Requires-Dist: ply==3.11
Requires-Dist: six==1.17.0
Requires-Dist: treelib==1.7.0
Requires-Dist: graphviz==0.20.3
Requires-Dist: more-itertools<=10.6.0
Requires-Dist: pydantic_mini==1.0.4
Requires-Dist: apscheduler<=3.11.0
Requires-Dist: typing-extensions==4.12.2
Provides-Extra: dev
Requires-Dist: coverage>=7.4.1; extra == "dev"
Requires-Dist: iniconfig==2.0.0; extra == "dev"
Requires-Dist: packaging==24.2; extra == "dev"
Requires-Dist: pluggy==1.5.0; extra == "dev"
Requires-Dist: pytest==8.3.4; extra == "dev"
Requires-Dist: pyflakes==3.2.0; extra == "dev"
Requires-Dist: mccabe==0.7.0; extra == "dev"
Requires-Dist: flake8==7.1.1; extra == "dev"
Requires-Dist: pycodestyle==2.12.1; extra == "dev"
Requires-Dist: flake8-black==0.3.6; extra == "dev"
Requires-Dist: black>=22.1.0; extra == "dev"
Requires-Dist: click==8.1.8; extra == "dev"
Requires-Dist: mypy-extensions==1.0.0; extra == "dev"
Requires-Dist: pathspec==0.12.1; extra == "dev"
Requires-Dist: platformdirs==4.3.6; extra == "dev"
Requires-Dist: redis==5.2.1; extra == "dev"
Provides-Extra: metrics
Requires-Dist: elasticsearch>=8.0.0; extra == "metrics"
Requires-Dist: prometheus-client>=0.20.0; extra == "metrics"
Requires-Dist: requests>=2.31.0; extra == "metrics"
Dynamic: license-file
